README.md
setup.py
roct/__init__.py
roct/base.py
roct/lsu_augmented.py
roct/maxsat.py
roct/milp.py
roct/upper_bound.py
roct.egg-info/PKG-INFO
roct.egg-info/SOURCES.txt
roct.egg-info/dependency_links.txt
roct.egg-info/requires.txt
roct.egg-info/top_level.txt
tests/__init__.py
tests/test_readme.py