Metadata-Version: 2.1
Name: roct
Version: 0.0.3
Summary: Robust Optimal Classification Trees
Home-page: https://github.com/tudelft-cda-lab/ROCT
Author: Daniel Vos
Author-email: D.A.Vos@tudelft.nl
License: UNKNOWN
Platform: UNKNOWN
Classifier: Programming Language :: Python :: 3
Classifier: License :: OSI Approved :: MIT License
Classifier: Operating System :: OS Independent
Requires-Python: >=3.6
